meta/request.py
rainhub_python_driver-0.1.0.dist-info/METADATA
rainhub_python_driver-0.1.0.dist-info/WHEEL
rainhub_python_driver-0.1.0.dist-info/top_level.txt
rainhub_python_driver-0.1.0.dist-info/RECORD
